opengate_core_novis.libs/libG4FR-63059174.so
opengate_core_novis.libs/libG4materials-22d6d9e2.so
opengate_core_novis.libs/libG4vis_management-e2cc9331.so
opengate_core_novis.libs/libG4clhep-26b0e212.so
opengate_core_novis.libs/libG4Tree-2faa0609.so
opengate_core_novis.libs/libG4ToolsSG-637f6278.so
opengate_core_novis.libs/libG4parmodels-aa00a863.so
opengate_core_novis.libs/libG4analysis-357a53a7.so
opengate_core_novis.libs/libG4geomtext-5ee83643.so
opengate_core_novis.libs/libfftw3_threads-1d56c0c3.so.3.3.2
opengate_core_novis.libs/libG4GMocren-73d60f00.so
opengate_core_novis.libs/libG4mctruth-de200e18.so
opengate_core_novis.libs/libG4readout-bb8f93be.so
opengate_core_novis.libs/libG4digits_hits-42d56c77.so
opengate_core_novis.libs/libG4zlib-e2cda8fc.so
opengate_core_novis.libs/libG4event-01c7640a.so
opengate_core_novis.libs/libG4geometry-ad08ee90.so
opengate_core_novis.libs/libG4tracking-3946b60e.so
opengate_core_novis.libs/libG4RayTracer-8ec9ca56.so
opengate_core_novis.libs/libG4graphics_reps-dbe4ca4b.so
opengate_core_novis.libs/libfftw3f-4367ce36.so.3.3.2
opengate_core_novis.libs/libG4interfaces-2369a2ef.so
opengate_core_novis.libs/libG4global-73545a6b.so
opengate_core_novis.libs/libG4processes-3f9d0729.so
opengate_core_novis.libs/libG4ptl-bcdf3b20.so.3.0.0
opengate_core_novis.libs/libG4visHepRep-162da713.so
opengate_core_novis.libs/libfftw3-17cc48a2.so.3.3.2
opengate_core_novis.libs/libG4run-9300d1eb.so
opengate_core_novis.libs/libG4track-c1a233fb.so
opengate_core_novis.libs/libG4particles-a1949402.so
opengate_core_novis.libs/libfftw3f_threads-de15b4b8.so.3.3.2
opengate_core_novis.libs/libG4modeling-ab48f04e.so
opengate_core_novis.libs/libG4intercoms-743be7dc.so
opengate_core_novis.libs/libG4error_propagation-f47eb802.so
opengate_core_novis.libs/libG4physicslists-d8171dcb.so
opengate_core_novis.libs/libG4VRML-96ddf187.so
opengate_core/g4DataSetup.py
opengate_core/testsDataSetup.py
opengate_core_novis-10.0.3.dist-info/WHEEL
opengate_core_novis-10.0.3.dist-info/top_level.txt
opengate_core_novis-10.0.3.dist-info/METADATA
opengate_core_novis-10.0.3.dist-info/RECORD
